droidsentinel/__init__.py
droidsentinel/main.py
droidsentinel-1.0.dist-info/METADATA
droidsentinel-1.0.dist-info/WHEEL
droidsentinel-1.0.dist-info/entry_points.txt
droidsentinel-1.0.dist-info/top_level.txt
droidsentinel-1.0.dist-info/RECORD
