Metadata-Version: 2.2
Name: droidsentinel
Version: 1.0
Summary: Automated Static Analysis of APKs
Home-page: https://github.com/ch3tanbug/DroidSentinel
Author: Chetan Kashyap
Author-email: chetanbug@duck.com
Classifier: Programming Language :: Python :: 3
Classifier: License :: OSI Approved :: MIT License
Classifier: Operating System :: OS Independent
Requires-Python: >=3.6
Requires-Dist: blinker==1.9.0
Requires-Dist: click==8.1.7
Requires-Dist: cryptography==44.0.0
Requires-Dist: dnspython==2.7.0
Requires-Dist: Flask==3.1.0
Requires-Dist: Flask-Cors==5.0.0
Requires-Dist: itsdangerous==2.2.0
Requires-Dist: Jinja2==3.1.4
Requires-Dist: joblib==1.4.2
Requires-Dist: MarkupSafe==3.0.2
Requires-Dist: MouseInfo==0.1.3
Requires-Dist: mpmath==1.3.0
Requires-Dist: nltk==3.9.1
Requires-Dist: numpy==2.2.0
Requires-Dist: packaging==24.2
Requires-Dist: pandas==2.2.3
Requires-Dist: PyAutoGUI==0.9.54
Requires-Dist: PyGetWindow==0.0.9
Requires-Dist: pymongo==4.10.1
Requires-Dist: PyMsgBox==1.0.9
Requires-Dist: pyngrok==7.2.3
Requires-Dist: pyperclip==1.9.0
Requires-Dist: PyRect==0.2.0
Requires-Dist: PyScreeze==1.0.1
Requires-Dist: python-dateutil==2.9.0.post0
Requires-Dist: pytweening==1.2.0
Requires-Dist: pytz==2024.2
Requires-Dist: PyYAML==6.0.2
Requires-Dist: regex==2024.11.6
Requires-Dist: rubicon-objc==0.4.9
Requires-Dist: scikit-learn==1.6.0
Requires-Dist: scipy==1.14.1
Requires-Dist: six==1.17.0
Requires-Dist: sympy==1.13.3
Requires-Dist: threadpoolctl==3.5.0
Requires-Dist: tqdm==4.67.1
Requires-Dist: tzdata==2024.2
Requires-Dist: Werkzeug==3.1.3
Requires-Dist: wheel
Dynamic: author
Dynamic: author-email
Dynamic: classifier
Dynamic: description
Dynamic: description-content-type
Dynamic: home-page
Dynamic: requires-dist
Dynamic: requires-python
Dynamic: summary
